README.md
setup.cfg
setup.py
PPark/__init__.py
PPark/constant.py
PPark/lexer.py
PPark.egg-info/PKG-INFO
PPark.egg-info/SOURCES.txt
PPark.egg-info/dependency_links.txt
PPark.egg-info/top_level.txt