Metadata-Version: 1.1
Name: PPark
Version: 1.0.1
Summary: Advanced Lexer
Home-page: https://github.com/aabbfive/PPark
Author: aabbfive
Author-email: diffyheart@gmail.com
License: MIT
Download-URL: https://github.com/aabbfive/PPark/releases
Keywords: lexer,ast,compiler
Platform: UNKNOWN
Classifier: Programming Language :: Python
Classifier: Development Status :: 4 - Beta
Classifier: License :: OSI Approved :: MIT License
Classifier: Natural Language :: English
Classifier: Programming Language :: Python :: 2
Classifier: Programming Language :: Python :: 3
Classifier: Topic :: Text Processing
